jupyterlab_robotmode/__init__.py
jupyterlab_robotmode/_version.py
jupyterlab_robotmode/labextension/package.json
jupyterlab_robotmode/labextension/static/480.00e5f6c8a59de2f63f89.js
jupyterlab_robotmode/labextension/static/568.980f4f5aedf3c209f942.js
jupyterlab_robotmode/labextension/static/73.f05d0042f204e45c45d0.js
jupyterlab_robotmode/labextension/static/remoteEntry.72b66241ab942c2073a5.js
jupyterlab_robotmode/labextension/static/style.js
jupyterlab_robotmode/labextension/static/third-party-licenses.json
jupyterlab_robotmode-0.4.0.data/data/share/jupyter/labextensions/@marketsquare/jupyterlab_robotmode/install.json
jupyterlab_robotmode-0.4.0.data/data/share/jupyter/labextensions/@marketsquare/jupyterlab_robotmode/package.json
jupyterlab_robotmode-0.4.0.data/data/share/jupyter/labextensions/@marketsquare/jupyterlab_robotmode/static/480.00e5f6c8a59de2f63f89.js
jupyterlab_robotmode-0.4.0.data/data/share/jupyter/labextensions/@marketsquare/jupyterlab_robotmode/static/568.980f4f5aedf3c209f942.js
jupyterlab_robotmode-0.4.0.data/data/share/jupyter/labextensions/@marketsquare/jupyterlab_robotmode/static/73.f05d0042f204e45c45d0.js
jupyterlab_robotmode-0.4.0.data/data/share/jupyter/labextensions/@marketsquare/jupyterlab_robotmode/static/remoteEntry.72b66241ab942c2073a5.js
jupyterlab_robotmode-0.4.0.data/data/share/jupyter/labextensions/@marketsquare/jupyterlab_robotmode/static/style.js
jupyterlab_robotmode-0.4.0.data/data/share/jupyter/labextensions/@marketsquare/jupyterlab_robotmode/static/third-party-licenses.json
jupyterlab_robotmode-0.4.0.dist-info/LICENSE
jupyterlab_robotmode-0.4.0.dist-info/METADATA
jupyterlab_robotmode-0.4.0.dist-info/WHEEL
jupyterlab_robotmode-0.4.0.dist-info/top_level.txt
jupyterlab_robotmode-0.4.0.dist-info/RECORD
