Metadata-Version: 2.1
Name: jupyterlab-robotmode
Version: 0.4.0
Summary: A JupyterLab extension which adds a CodeMirror mode for Robot Framework syntax
Home-page: https://github.com/MarketSquare/jupyterlab_robotmode
Author: MarketSquare
License: BSD-3-Clause
Project-URL: Source, https://github.com/MarketSquare/jupyterlab_robotmode
Project-URL: Tracker, https://github.com/MarketSquare/jupyterlab_robotmode/issues
Keywords: Jupyter,JupyterLab,JupyterLab3
Platform: Linux
Platform: Mac OS X
Platform: Windows
Classifier: License :: OSI Approved :: BSD License
Classifier: Programming Language :: Python
Classifier: Programming Language :: Python :: 3
Classifier: Programming Language :: Python :: 3.8
Classifier: Programming Language :: Python :: 3.9
Classifier: Programming Language :: Python :: 3.10
Classifier: Programming Language :: Python :: 3.11
Classifier: Framework :: Jupyter
Classifier: Framework :: Jupyter :: JupyterLab
Classifier: Framework :: Jupyter :: JupyterLab :: 3
Classifier: Framework :: Jupyter :: JupyterLab :: Extensions
Classifier: Framework :: Jupyter :: JupyterLab :: Extensions :: Prebuilt
Classifier: Framework :: Robot Framework
Requires-Python: >=3.8
License-File: LICENSE
Requires-Dist: jupyterlab (<4,>=3)
